molecular_structure/__init__.py
molecular_structure/config/__init__.py
molecular_structure/config/molecule_parameters.py
molecular_structure/src/__init__.py
molecular_structure/src/energy_levels.py
molecular_structure/src/hamiltonian_builders.py
molecular_structure/src/matrix_elements_sym.py
molecular_structure/src/molecule_library_class.py
molecular_structure/utils/__init__.py
molecular_structure/utils/case_bBJ_MEs.py
molecular_structure/utils/cpt_sims.py
molecular_structure/utils/linear_algebra.py
molecular_structure/utils/matrix_elements.py
molecular_structure/utils/quantum_numbers.py
tests/__init__.py
tests/basic_test.py
molecular_structure-0.1.0.dist-info/LICENSE
molecular_structure-0.1.0.dist-info/METADATA
molecular_structure-0.1.0.dist-info/WHEEL
molecular_structure-0.1.0.dist-info/top_level.txt
molecular_structure-0.1.0.dist-info/RECORD
