Metadata-Version: 2.1
Name: molecular_structure
Version: 0.1.0
Summary: A package to work with molecular structures
Author-email: Arian Jadbabaie <arianjad@mit.edu>, Jose M Munoz <munozariasjm@gmail.com>
Project-URL: Homepage, https://github.com/munozariasjm/Molecule-Structure
License-File: LICENSE
